irpjs/__init__.py
irpjs/irp.py
irpjs-0.0.2.dist-info/COPYING.MPL
irpjs-0.0.2.dist-info/METADATA
irpjs-0.0.2.dist-info/WHEEL
irpjs-0.0.2.dist-info/top_level.txt
irpjs-0.0.2.dist-info/RECORD
