Metadata-Version: 2.1
Name: irpjs
Version: 0.0.2
Summary: Server for the JavaScript LibreOffice Impress Remote.
Home-page: https://rptr.github.io/gsoc/
Author: Rasmus P J
Author-email: wasmus@zom.bi
License: UNKNOWN
Platform: UNKNOWN
Requires-Dist: gevent-websocket
